{
  "info": {
    "_postman_id": "94c537b8-0cea-450e-8da2-3429a0cf71e3",
    "name": "Gateway",
    "schema": "https://schema.getpostman.com/json/collection/v2.1.0/collection.json",
    "_exporter_id": "54380956",
    "_collection_link": "https://go.postman.co/collection/54380956-94c537b8-0cea-450e-8da2-3429a0cf71e3?source=collection_link"
  },
  "item": [
    {
      "name": "http://localhost:9000/app/info",
      "request": {
        "auth": {
          "type": "noauth"
        },
        "method": "GET",
        "header": [],
        "url": {
          "raw": "http://localhost:9000/app/info",
          "protocol": "http",
          "host": [
            "localhost"
          ],
          "port": "9000",
          "path": [
            "app",
            "info"
          ],
          "query": [
            {
              "key": "Authorization",
              "value": "Bearer eyJhbGciOiJIUzI1NiJ9.eyJzdWIiOiJhZG1pbiIsImlhdCI6MTc3NzYwMzk0MiwiZXhwIjoxNzc3NjA3NTQyfQ.BW9dYSJxviKCgLvvDAIsRzr6T6xbV8Ie0T2xBqL33Do",
              "type": "text",
              "disabled": true
            }
          ]
        }
      },
      "response": []
    },
    {
      "name": "http://localhost:9000/auth/login",
      "request": {
        "auth": {
          "type": "basic",
          "basic": [
            {
              "key": "password",
              "value": "admin",
              "type": "string"
            },
            {
              "key": "username",
              "value": "admin",
              "type": "string"
            }
          ]
        },
        "method": "POST",
        "header": [],
        "body": {
          "mode": "raw",
          "raw": "{\r\n    \"username\":\"admin\",\r\n    \"password\":\"admin\"\r\n}",
          "options": {
            "raw": {
              "language": "json"
            }
          }
        },
        "url": {
          "raw": "http://localhost:9000/auth/login",
          "protocol": "http",
          "host": [
            "localhost"
          ],
          "port": "9000",
          "path": [
            "auth",
            "login"
          ]
        }
      },
      "response": []
    },
    {
      "name": "gateway-exceed",
      "event": [
        {
          "listen": "test",
          "script": {
            "exec": [
              "pm.test(\"Status code is 200\", function () {",
              "    pm.response.to.have.status(200);",
              "});"
            ],
            "type": "text/javascript",
            "packages": {},
            "requests": {}
          }
        }
      ],
      "request": {
        "auth": {
          "type": "bearer",
          "bearer": [
            {
              "key": "token",
              "value": "eyJhbGciOiJIUzI1NiJ9.eyJzdWIiOiJhZG1pbiIsImlhdCI6MTc3NzYzOTg1NywiZXhwIjoxNzc3NjQzNDU3fQ.aBwlACOl5YOMTliWHajcdhDaPW3woouuXtLXf4NBMrQ",
              "type": "string"
            }
          ]
        },
        "method": "GET",
        "header": [],
        "url": {
          "raw": "localhost:9000/user/test",
          "host": [
            "localhost"
          ],
          "port": "9000",
          "path": [
            "user",
            "test"
          ]
        }
      },
      "response": []
    },
    {
      "name": "/user/details/URS-1266",
      "request": {
        "auth": {
          "type": "bearer",
          "bearer": [
            {
              "key": "token",
              "value": "eyJhbGciOiJIUzI1NiJ9.eyJzdWIiOiJhZG1pbiIsImlhdCI6MTc3ODIyOTY4NiwiZXhwIjoxNzc4MjMzMjg2fQ.V6hQ5BM1Ty_EZVdwsuRiJib03yqKTkLFaSgn4WLItXg",
              "type": "string"
            }
          ]
        },
        "method": "GET",
        "header": [],
        "url": {
          "raw": "localhost:9000/user/detail/URS-12048",
          "host": [
            "localhost"
          ],
          "port": "9000",
          "path": [
            "user",
            "detail",
            "URS-12048"
          ]
        }
      },
      "response": []
    },
    {
      "name": "/user/list/OPEN",
      "request": {
        "auth": {
          "type": "bearer",
          "bearer": [
            {
              "key": "token",
              "value": "eyJhbGciOiJIUzI1NiJ9.eyJzdWIiOiJhZG1pbiIsImlhdCI6MTc3ODIyOTY4NiwiZXhwIjoxNzc4MjMzMjg2fQ.V6hQ5BM1Ty_EZVdwsuRiJib03yqKTkLFaSgn4WLItXg",
              "type": "string"
            }
          ]
        },
        "method": "GET",
        "header": [],
        "url": {
          "raw": "localhost:9000/user/list/OPEN",
          "host": [
            "localhost"
          ],
          "port": "9000",
          "path": [
            "user",
            "list",
            "OPEN"
          ]
        }
      },
      "response": []
    },
    {
      "name": "/user/create",
      "request": {
        "auth": {
          "type": "bearer",
          "bearer": [
            {
              "key": "token",
              "value": "eyJhbGciOiJIUzI1NiJ9.eyJzdWIiOiJhZG1pbiIsImlhdCI6MTc3ODE1MjY1MywiZXhwIjoxNzc4MTU2MjUzfQ.lWCHov3qfRbur3jQrtQBkk3fFtDU1YQ9V3hYaDWocPc",
              "type": "string"
            }
          ]
        },
        "method": "POST",
        "header": [],
        "body": {
          "mode": "raw",
          "raw": "{\r\n        \"discription\": \"Test KK  Global Log Report Date Based\",\r\n        \"projectName\": \"sab-plm-services\",\r\n        \"startDate\": \"\",\r\n        \"createDate\": \"02-10-2023 11:47:44\",\r\n        \"updateDate\": \"\",\r\n        \"closedDate\": \"\",\r\n        \"storyPoint\": 13,\r\n        \"targetDate\": \"\",\r\n        \"developingSkill\": \"Spring Boot\",\r\n        \"assigned\": \"Sunil\",\r\n        \"gitBranch\": \"\",\r\n        \"gitUrl\": \"\",\r\n        \"status\": \"Open\",\r\n        \"epic\": \"\",\r\n        \"project\": \"scratch\",\r\n        \"severity\": \"Medium\",\r\n        \"expectedFixedVersion\": \"\",\r\n        \"actualFixedVersion\": \"\",\r\n        \"linkedStories\": \"\",\r\n        \"effort\": null,\r\n        \"lables\": null,\r\n        \"taskList\": null,\r\n        \"logList\": null,\r\n        \"commentsList\": null,\r\n        \"activityList\": null,\r\n        \"issueList\": null,\r\n        \"upDateDate\": \"\"\r\n    },",
          "options": {
            "raw": {
              "language": "json"
            }
          }
        },
        "url": {
          "raw": "localhost:9000/user/create",
          "host": [
            "localhost"
          ],
          "port": "9000",
          "path": [
            "user",
            "create"
          ]
        }
      },
      "response": []
    }
  ]
}